{
  "display": {
    "icon": {
      "item": "minecraft:bamboo"
    },
    "title": "Jungle Plant",
    "description": "Obtain Bamboo",
    "frame": "task",
    "show_toast": true,
    "announce_to_chat": true,
    "hidden": false
  },
  "task": {
    "experience": 10
  },
  "parent": "foodmod:foodmod",
  "criteria": {
    "requirement": {
      "trigger": "minecraft:inventory_changed",
      "conditions": {
        "items": [
          {
            "items": [
              "minecraft:bamboo"
            ]
          }
        ]
      }
    }
  }
}










